d64gfx/D64Gfx.py
d64gfx-3.0.1.dist-info/METADATA
d64gfx-3.0.1.dist-info/WHEEL
d64gfx-3.0.1.dist-info/top_level.txt
d64gfx-3.0.1.dist-info/RECORD
