Metadata-Version: 2.1
Name: d64gfx
Version: 3.0.1
Summary: Cenbe's Commodore 64 Disk Image Library (graphics routines)
Author-email: Glenn Holmer <cenbe@protonmail.com>
Project-URL: Repository, https://gitlab.com/Cenbe/d64gfx.git
Project-URL: Documentation, https://www.lyonlabs.org/pydoc/d64gfx/
Keywords: Commodore,GEOS
Classifier: Programming Language :: Python :: 3
Classifier: Development Status :: 5 - Production/Stable
Requires-Python: >=3.11
Requires-Dist: requests
Requires-Dist: d64py >=3.0.3
Requires-Dist: importlib-metadata ; python_version < "3.11"
